lk_utils/__init__.py
lk_utils/__main__.py
lk_utils/_subset_yaml_parser.py
lk_utils/binding/__init__.py
lk_utils/binding/binding.py
lk_utils/binding/reactive.py
lk_utils/binding/signal.py
lk_utils/chunk.py
lk_utils/common_typing.py
lk_utils/filesys/__init__.py
lk_utils/filesys/finder.py
lk_utils/filesys/main.py
lk_utils/filesys/shutil.py
lk_utils/importer.py
lk_utils/io.py
lk_utils/ipython.py
lk_utils/pycompatible.py
lk_utils/subproc/__init__.py
lk_utils/subproc/background_activities.py
lk_utils/subproc/coroutine.py
lk_utils/subproc/multiprocess.py
lk_utils/subproc/promise.py
lk_utils/subproc/subprocess.py
lk_utils/subproc/threading.py
lk_utils/textwrap.py
lk_utils/time_utils/__init__.py
lk_utils/time_utils/time.py
lk_utils/time_utils/timeit.py
lk_utils/time_utils/timer.py
lk_utils/time_utils/timer2.py
lk_utils-3.4.3.dist-info/METADATA
lk_utils-3.4.3.dist-info/WHEEL
lk_utils-3.4.3.dist-info/RECORD
