Metadata-Version: 2.3
Name: lk-utils
Version: 3.4.3
Summary: LK Utils is a set of utility wrappers made for data processing.
License: MIT
Author: Likianta
Author-email: likianta@foxmail.com
Requires-Python: >=3.8
Classifier: License :: OSI Approved :: MIT License
Classifier: Programming Language :: Python :: 3
Classifier: Programming Language :: Python :: 3.8
Classifier: Programming Language :: Python :: 3.9
Classifier: Programming Language :: Python :: 3.10
Classifier: Programming Language :: Python :: 3.11
Classifier: Programming Language :: Python :: 3.12
Classifier: Programming Language :: Python :: 3.13
Provides-Extra: all
Provides-Extra: dbg
Provides-Extra: exl
Provides-Extra: io
Provides-Extra: tml
Requires-Dist: argsense (>=1.1.0,<2.0.0)
Requires-Dist: ipython ; extra == "all"
Requires-Dist: ipython ; extra == "dbg"
Requires-Dist: lk-logger (>=6.0.6,<7.0.0)
Requires-Dist: psutil (>=6.0.0)
Requires-Dist: pyyaml (>=6.0.0,<7.0.0)
Requires-Dist: rich (>=13.9.0)
Requires-Dist: toml ; extra == "all"
Requires-Dist: toml ; extra == "io"
Requires-Dist: toml ; extra == "tml"
Requires-Dist: typing-extensions (>=4.0.0,<5.0.0)
Requires-Dist: xlrd (==1.2.0) ; extra == "all"
Requires-Dist: xlrd (==1.2.0) ; extra == "exl"
Requires-Dist: xlrd (==1.2.0) ; extra == "io"
Requires-Dist: xlsxwriter ; extra == "all"
Requires-Dist: xlsxwriter ; extra == "exl"
Requires-Dist: xlsxwriter ; extra == "io"
Project-URL: Homepage, https://github.com/likianta/lk-utils
